CHANGELOG.md
MANIFEST.in
README.md
setup.cfg
setup.py
versioneer.py
src/libreflow/__init__.py
src/libreflow.extensions.desert.scene_builder.egg-info/PKG-INFO
src/libreflow.extensions.desert.scene_builder.egg-info/SOURCES.txt
src/libreflow.extensions.desert.scene_builder.egg-info/dependency_links.txt
src/libreflow.extensions.desert.scene_builder.egg-info/top_level.txt
src/libreflow/extensions/__init__.py
src/libreflow/extensions/desert/__init__.py
src/libreflow/extensions/desert/scene_builder/__init__.py
src/libreflow/extensions/desert/scene_builder/_version.py
src/libreflow/extensions/desert/scene_builder/build_utils.py